{
  "id": "v2-baby-feelings-043",
  "title": "Lily's Colorful Feelings",
  "ageTier": "baby",
  "ageRange": [
    1,
    2
  ],
  "genre": [
    "feelings",
    "colors"
  ],
  "wordCount": 91,
  "readingLevel": "Pre-K",
  "synopsis": "Baby Lily experiences different emotions throughout her day, each represented by beautiful colors that swirl around her as she feels happy, sad, and angry.",
  "coverImage": "covers/v2-baby-feelings-043.webp",
  "chapters": [
    {
      "title": "Lily's Colorful Day",
      "pages": [
        {
          "text": "This is Lily. She feels many things every day. Her feelings have colors!",
          "illustration": {
            "description": "A young girl with long curly auburn hair, fair skin with light freckles, green eyes standing in the center with swirls of different colored emotions gently floating around her - yellow happiness, blue sadness, and red anger in soft abstract patterns",
            "alt": "Lily surrounded by colorful emotion swirls",
            "layout": "full-page"
          }
        },
        {
          "text": "When Lily is happy, she sees bright yellow! Like sunshine all around her. Happy feels warm and bright.",
          "illustration": {
            "description": "A smiling girl with long curly auburn hair, fair skin with light freckles, green eyes dancing joyfully as golden yellow sunshine rays and cheerful swirls surround her against a bright yellow background with sparkles",
            "alt": "Happy Lily surrounded by yellow sunshine",
            "layout": "full-page"
          }
        },
        {
          "text": "Sometimes Lily feels sad. Then she sees soft blue, like gentle rain falling down. Sad feels quiet and cool.",
          "illustration": {
            "description": "A girl with long curly auburn hair, fair skin with light freckles, green eyes sitting quietly with a gentle frown as soft blue raindrops and misty blue clouds float around her in a soothing blue atmosphere",
            "alt": "Sad Lily with blue rain around her",
            "layout": "full-page"
          }
        },
        {
          "text": "When Lily gets angry, she sees red swirls spinning fast! Angry feels hot and strong like fire.",
          "illustration": {
            "description": "A girl with long curly auburn hair, fair skin with light freckles, green eyes with crossed arms and a frown as bold red swirls and zigzag patterns whirl energetically around her against a red background",
            "alt": "Angry Lily with red swirls",
            "layout": "full-page"
          }
        },
        {
          "text": "All feelings are okay. Yellow happy, blue sad, red angry - they're all part of Lily. Colors help her understand how she feels inside.",
          "illustration": {
            "description": "A peaceful girl with long curly auburn hair, fair skin with light freckles, green eyes sitting calmly as all three emotion colors - yellow, blue, and red - blend harmoniously in gentle, balanced swirls around her",
            "alt": "Lily with all her colorful feelings in harmony",
            "layout": "full-page"
          }
        }
      ]
    }
  ],
  "metadata": {
    "themes": [
      "emotional awareness",
      "color recognition",
      "self-understanding",
      "feelings acceptance"
    ],
    "contentWarnings": [],
    "generatedAt": "2026-04-09",
    "illustrationStyle": "emotion mapped colors, angry red swirls, sad blue rain, happy yellow sunshine, abstract emotion backgrounds, Inside Out inspired, feeling visualization, color psychology"
  },
  "quiz": {
    "questions": [
      {
        "id": "q1",
        "question": "What color does Lily see when she's happy?",
        "choices": [
          "Yellow",
          "Blue",
          "Red"
        ],
        "correctIndex": 0,
        "explanation": "When Lily is happy, she sees bright yellow like sunshine!"
      },
      {
        "id": "q2",
        "question": "What does sad feel like for Lily?",
        "choices": [
          "Hot and strong",
          "Quiet and cool",
          "Bright and warm"
        ],
        "correctIndex": 1,
        "explanation": "Sad feels quiet and cool like gentle blue rain."
      },
      {
        "id": "q3",
        "question": "Are all of Lily's feelings okay?",
        "choices": [
          "Yes",
          "No"
        ],
        "correctIndex": 0,
        "explanation": "Yes! All feelings are okay - happy, sad, and angry are all part of Lily."
      }
    ]
  },
  "puzzle": {
    "pages": [
      {
        "pageIndex": 1,
        "blanks": [
          {
            "wordIndex": 8,
            "correctWord": "yellow",
            "distractors": [
              "red",
              "blue"
            ]
          }
        ]
      },
      {
        "pageIndex": 2,
        "blanks": [
          {
            "wordIndex": 7,
            "correctWord": "blue",
            "distractors": [
              "yellow",
              "green"
            ]
          }
        ]
      }
    ]
  }
}